Metadata-Version: 1.1
Name: color-convert
Version: 1.0
Summary: Color Conversion
Home-page: https://github.com/zhenzi0322/color-convert
Author: Yu Zhen
Author-email: 82131529@qq.com
License: MIT License
Keywords: color,color-convert,convert
Platform: UNKNOWN
Classifier: Programming Language :: Python :: 3.7
Classifier: Operating System :: MacOS :: MacOS X
Classifier: Operating System :: POSIX :: Linux
